Metadata-Version: 2.1
Name: glacier-centerlines
Version: 0.5.2
Summary: Compute glacier centerlines using RGI data and a well known algorithm (see documentetion)
Home-page: UNKNOWN
Author: Francesc Roura Adserias @OGGM developpers
Author-email: info@oggm.org
License: UNKNOWN
Platform: UNKNOWN
